PyQSPICE/__init__.py
PyQSPICE/qspice.py
PyQSPICE-2024.5.14.dist-info/LICENSE
PyQSPICE-2024.5.14.dist-info/METADATA
PyQSPICE-2024.5.14.dist-info/WHEEL
PyQSPICE-2024.5.14.dist-info/top_level.txt
PyQSPICE-2024.5.14.dist-info/RECORD
