Metadata-Version: 2.1
Name: PyQSPICE
Version: 2024.5.14
Summary: Python Wrapper for QSPICE
Author: Masashi Nogawa
License: Qorvo "PyQSPICE" Software License Agreement
Project-URL: Homepage, https://github.com/Qorvo/PyQSPICE
Project-URL: License, https://github.com/Qorvo/PyQSPICE/LICENSE
Project-URL: QSPICE, https://www.qorvo.com/design-hub/design-tools/interactive/qspice
Keywords: QSPICE,Qorvo,SPICE,LTSpice
Classifier: Programming Language :: Python :: 3
Classifier: License :: Other/Proprietary License
Requires-Python: >=3.8
License-File: LICENSE
Requires-Dist: pandas
Requires-Dist: matplotlib
